comicParser/__init__.py
comicParser/comicParser.py
comicParser/main.py
comic_parser-1.0.dist-info/LICENSE.txt
comic_parser-1.0.dist-info/METADATA
comic_parser-1.0.dist-info/WHEEL
comic_parser-1.0.dist-info/entry_points.txt
comic_parser-1.0.dist-info/top_level.txt
comic_parser-1.0.dist-info/RECORD
